schematypes/__init__.py
schematypes/_version.py
schematypes/dicts.py
schematypes/lists.py
schematypes/objects.py
schematypes/schemas.py
schematypes/strings.py
schematypes-0.0.1.dist-info/METADATA
schematypes-0.0.1.dist-info/WHEEL
schematypes-0.0.1.dist-info/top_level.txt
schematypes-0.0.1.dist-info/RECORD
